nonebot_plugin_fix_qq_img_ssl-0.1.1.dist-info/METADATA
nonebot_plugin_fix_qq_img_ssl-0.1.1.dist-info/WHEEL
nonebot_plugin_fix_qq_img_ssl-0.1.1.dist-info/entry_points.txt
nonebot_plugin_fix_qq_img_ssl-0.1.1.dist-info/licenses/LICENSE
nonebot_plugin_fix_qq_img_ssl/__init__.py
nonebot_plugin_fix_qq_img_ssl/__main__.py
nonebot_plugin_fix_qq_img_ssl/config.py
nonebot_plugin_fix_qq_img_ssl-0.1.1.dist-info/RECORD
