Metadata-Version: 2.1
Name: nonebot-plugin-fix-qq-img-ssl
Version: 0.1.1
Summary: Fix QQ image hosting SSL issue
Author-Email: LgCookie <lgc2333@126.com>
License: MIT
Project-URL: homepage, https://github.com/lgc-NB2Dev/nonebot-plugin-fix-qq-img-ssl
Requires-Python: <4.0,>=3.9
Requires-Dist: nonebot2>=2.4.1
Requires-Dist: httpx>=0.28.0
Requires-Dist: aiohttp>=3.11.18
